dcm_check/__init__.py
dcm_check/compliance.py
dcm_check/io.py
dcm_check/mapping.py
dcm_check/models.py
dcm_check/utils.py
dcm_check/tests/__init__.py
dcm_check/tests/test_io.py
dcm_check/tests/test_models.py
dcm_check/tests/test_ref_dicom.py
dcm_check/tests/fixtures/__init__.py
dcm_check/tests/fixtures/fixtures.py
dcm_check/tests/fixtures/ref_pydantic.py
dcm_check/tests/fixtures/ref_pydantic_cross_series_checks.py
dcm_check/tests/fixtures/ref_pydantic_no_models.py
dcm_check-0.1.7.dist-info/LICENSE
dcm_check-0.1.7.dist-info/METADATA
dcm_check-0.1.7.dist-info/WHEEL
dcm_check-0.1.7.dist-info/entry_points.txt
dcm_check-0.1.7.dist-info/top_level.txt
dcm_check-0.1.7.dist-info/RECORD
